asdk_plugin_investment_research/__init__.py
asdk_plugin_investment_research/api_registry.py
asdk_plugin_investment_research/domain_apis_list.json
asdk_plugin_investment_research/agraph/__init__.py
asdk_plugin_investment_research/agraph/investment_research/__init__.py
asdk_plugin_investment_research/agraph/investment_research/analyst/__init__.py
asdk_plugin_investment_research/agraph/investment_research/analyst/coverage/__init__.py
asdk_plugin_investment_research/agraph/investment_research/analyst/coverage/v1/__init__.py
asdk_plugin_investment_research/agraph/investment_research/analyst/coverage/v1/AnalystCoverageAPI/__init__.py
asdk_plugin_investment_research/agraph/investment_research/analyst/coverage/v1/AnalystCoverageAPI/api_client.py
asdk_plugin_investment_research/agraph/investment_research/analyst/coverage/v1/AnalystCoverageAPI/api_response.py
asdk_plugin_investment_research/agraph/investment_research/analyst/coverage/v1/AnalystCoverageAPI/configuration.py
asdk_plugin_investment_research/agraph/investment_research/analyst/coverage/v1/AnalystCoverageAPI/exceptions.py
asdk_plugin_investment_research/agraph/investment_research/analyst/coverage/v1/AnalystCoverageAPI/rest.py
asdk_plugin_investment_research/agraph/investment_research/analyst/coverage/v1/AnalystCoverageAPI/swagger.json
asdk_plugin_investment_research/agraph/investment_research/analyst/coverage/v1/AnalystCoverageAPI/api/__init__.py
asdk_plugin_investment_research/agraph/investment_research/analyst/coverage/v1/AnalystCoverageAPI/api/default_analyst_coverage_api.py
asdk_plugin_investment_research/agraph/investment_research/analyst/coverage/v1/AnalystCoverageAPI/models/__init__.py
asdk_plugin_investment_research/agraph/investment_research/analyst/coverage/v1/AnalystCoverageAPI/models/analyst_coverage_api_create_analyst_coverage400_response.py
asdk_plugin_investment_research/agraph/investment_research/analyst/coverage/v1/AnalystCoverageAPI/models/any.py
asdk_plugin_investment_research-2.0.0b2.dist-info/METADATA
asdk_plugin_investment_research-2.0.0b2.dist-info/WHEEL
asdk_plugin_investment_research-2.0.0b2.dist-info/top_level.txt
asdk_plugin_investment_research-2.0.0b2.dist-info/RECORD
